{"results": {"channels": [{"alternatives": [{"transcript": "You know, five years ago, when I started Stratton Oakmont with Donnie Azoff, I knew the day would eventually come where I'd have to be moving on. And it's truly with a heavy heart that I'm here to say that that day is finally here. I want to thank you all for your years of loyalty and admiration. But the point is this. Under Donnie's leadership, along with Nikki Koskov and Robbie Feinberg moving into key management positions, this place really is going to be better than ever. That I promise you. Okay? This is Ellis island here, people. I don't care who you are, where you're from, whether your relatives came over on the fucking mayflower or an inner tube from Haiti, this right here is the land of opportunity. Stratton Oakmont is America. All of you know Kimmy Belzer, right? Yes, we do. Fuck you. Come on, Kimmy. What you probably didn't know is Kimmy was one of the first brokers here. One of Stratton's original 20. Now, most of you met Kimmy, the beautiful, sophisticated woman that she is today. A woman that wears $3,000 Armani suits, who drives a brand new Mercedesbenz, a woman who spends her winters in the Bahamas and her summers in the Hamptons. That's not the Kimmy that I met. The Kimmy that I met didn't have two nickels to rub together. She was a single mom on the balls of her ass with an eight year old son. Okay? She was three months behind on her rent. And when she came to me and asked me for a job, she asked for a $5,000 advance just so she could pay his son's tuition. What? I do, Kimmy? Go on, tell me. You wrote me a check for $25,000. That's right. And you know why that is? It's because I believed in you. It's because I believed in you, Kimmy, just like I believe in each and every one of you here today. I fucking love you, Jordan. I fucking love you. I love you. I fucking love you, too. I fucking love you, too. And I love all of you. I love all of you from the bottom of my arm. I mean that. Because for years, I've been telling you guys never to take no for an answer, right? To keep pushing, to never hang up the phone until you get what you want. Because you all deserve it. This fucking deal that I'm about to sign, barring me from the securities industry, barring me from Stratton, my home. The fuck is that? I'll tell you what it is? It's me taking no for an answer. It's them selling me, not the other way around. It's me being a hypocrite, is what it is. It. You know what? I'm not leaving. I'm not leaving. I'm not fucking leaving you. The show goes on. This is my home. They're gonna need a fucking wrecking ball to take me out of here. They're going to need to send you the national God of fucking SWAT team. Because I ain't going nowhere. Feet to the rocket of inspector seven. One step beyond. It was our time to party big. And just as Brad was released from jail, too. I apologized, even offered to pay him for his time in the can. But he said no, that he was out. He didn't want any part of us. Sad thing was, two years later he was dead. Massive heart attack. 35. Same age Mozart died. Not that they have a hell of a lot in common, but. Anyway, I don't know why that came to mind. Within days, subpoenas started flying. Notices to produce documents, depositions, you name it. Donnie couldn't drink water fast enough. United States government wants to get me a subpoena? Here's what we do with subpoenas in Stratton. Fuck you, USA. Fuck you. Fuck you. Fuck you. Fuck you. Fuck you. Fuck you. Fuck you. Jordan Belfort. Olden, that's a nice name. Thank you very much for that. What kind of name is that? That is my name. I do not recall that. I do not recall that. Okay. Mr. Ming, thank you for coming in today. You to finish the rest of that danish, can I have that? They interrogated everybody. Had a low blood sugar divert thing. It went on for months. It was a total fucking harassment. Not a single stratnite cracked. Gladys Carrera? Doesn't ring a bell? Sorry, I have no recommendation of that. No, Jack, no idea. I don't recall that transaction. Do you guys have any molt? Absolutely not. Francis Ortiz you called so many times, I just thought you might remember that either. Right. Would you remember any of that? I do not recall any of that. This Abdul. I do not recall. No? I don't recall. I do not. It's a long phone call. Just wondering if you have any memory of. You know, we've talked to several of the employees at this firm, and nobody can recall anything about the Steve Madden IPO. I think it's odd. Do you recall carnage Corporation? You do recall it? No, I don't recall that at all. Excuse me, I have to ask, is that your real hair? Are you going to say anything about that? Are you going to comment on my hair? Is that how we're doing? Is this personal questions? I thought wondering why you would wear something like that. Yes. I have a rare condition which requires me to drink one of those every 15 minutes. Please. We were specifically advised not to leave the country. So we took our wives to Italy. We figured we were safer working from overseas, giving orders to Rugrat. Nobody could arrest us. And nobody could prove I was still running Stratton from a yacht. Hey, Rugrat. Bonjour. You bob headed Eagle, how you doing? Donnie, Donnie, listen, we have a problem, okay? Your friend Steve Madden is unloading shares. What do you shade? Who told you that? What's going on?", "words": [{"word": "You", "onset": 27.65, "offset": 27.814, "confidence": 0.73}, {"word": "know,", "onset": 27.852, "offset": 28.44, "confidence": 0.98417}, {"word": "five", "onset": 29.29, "offset": 29.702, "confidence": 1.0}, {"word": "years", "onset": 29.756, "offset": 29.974, "confidence": 0.99998}, {"word": "ago,", "onset": 30.012, "offset": 30.262, "confidence": 0.99997}, {"word": "when", "onset": 30.316, "offset": 30.486, "confidence": 0.99995}, {"word": "I", "onset": 30.508, "offset": 30.694, "confidence": 1.0}, {"word": "started", "onset": 30.732, "offset": 31.03, "confidence": 1.0}, {"word": "Stratton", "onset": 31.1, "offset": 31.506, "confidence": 0.95903}, {"word": "Oakmont", "onset": 31.538, "offset": 32.114, "confidence": 0.49989}, {"word": "with", "onset": 32.162, "offset": 32.614, "confidence": 1.0}, {"word": "Donnie", "onset": 32.732, "offset": 33.186, "confidence": 0.55972}, {"word": "Azoff,", "onset": 33.218, "offset": 33.842, "confidence": 0.53207}, {"word": "I", "onset": 33.906, "offset": 34.038, "confidence": 1.0}, {"word": "knew", "onset": 34.044, "offset": 34.214, "confidence": 0.76355}, {"word": "the", "onset": 34.252, "offset": 34.406, "confidence": 1.0}, {"word": "day", "onset": 34.428, "offset": 34.566, "confidence": 1.0}, {"word": "would", "onset": 34.588, "offset": 34.726, "confidence": 0.99677}, {"word": "eventually", "onset": 34.748, "offset": 35.154, "confidence": 0.78788}, {"word": "come", "onset": 35.202, "offset": 35.414, "confidence": 0.99996}, {"word": "where", "onset": 35.452, "offset": 35.606, "confidence": 0.99986}, {"word": "I'd", "onset": 35.628, "offset": 35.778, "confidence": 0.99935}, {"word": "have", "onset": 35.794, "offset": 35.926, "confidence": 0.99991}, {"word": "to", "onset": 35.948, "offset": 36.038, "confidence": 1.0}, {"word": "be", "onset": 36.044, "offset": 36.166, "confidence": 0.99994}, {"word": "moving", "onset": 36.188, "offset": 36.422, "confidence": 0.99995}, {"word": "on.", "onset": 36.476, "offset": 37.08, "confidence": 1.0}, {"word": "And", "onset": 39.53, "offset": 39.846, "confidence": 0.99}, {"word": "it's", "onset": 39.868, "offset": 40.066, "confidence": 0.91083}, {"word": "truly", "onset": 40.098, "offset": 40.386, "confidence": 0.99968}, {"word": "with", "onset": 40.418, "offset": 40.566, "confidence": 1.0}, {"word": "a", "onset": 40.588, "offset": 40.678, "confidence": 1.0}, {"word": "heavy", "onset": 40.684, "offset": 40.898, "confidence": 0.99992}, {"word": "heart", "onset": 40.914, "offset": 41.142, "confidence": 0.67235}, {"word": "that", "onset": 41.196, "offset": 41.462, "confidence": 0.99904}, {"word": "I'm", "onset": 41.516, "offset": 41.746, "confidence": 0.988}, {"word": "here", "onset": 41.778, "offset": 41.926, "confidence": 0.99997}, {"word": "to", "onset": 41.948, "offset": 42.086, "confidence": 1.0}, {"word": "say", "onset": 42.108, "offset": 42.246, "confidence": 0.9995}, {"word": "that", "onset": 42.268, "offset": 42.84, "confidence": 0.92677}, {"word": "that", "onset": 45.53, "offset": 45.846, "confidence": 0.97}, {"word": "day", "onset": 45.868, "offset": 46.054, "confidence": 1.0}, {"word": "is", "onset": 46.092, "offset": 46.246, "confidence": 0.99887}, {"word": "finally", "onset": 46.268, "offset": 46.502, "confidence": 0.99985}, {"word": "here.", "onset": 46.556, "offset": 47.16, "confidence": 0.95418}, {"word": "I", "onset": 51.89, "offset": 52.158, "confidence": 0.84}, {"word": "want", "onset": 52.164, "offset": 52.238, "confidence": 0.97218}, {"word": "to", "onset": 52.244, "offset": 52.366, "confidence": 0.98}, {"word": "thank", "onset": 52.388, "offset": 52.574, "confidence": 0.99997}, {"word": "you", "onset": 52.612, "offset": 52.814, "confidence": 0.72}, {"word": "all", "onset": 52.852, "offset": 53.102, "confidence": 1.0}, {"word": "for", "onset": 53.156, "offset": 53.326, "confidence": 1.0}, {"word": "your", "onset": 53.348, "offset": 53.87, "confidence": 0.51}, {"word": "years", "onset": 54.02, "offset": 54.382, "confidence": 0.99987}, {"word": "of", "onset": 54.436, "offset": 54.654, "confidence": 0.96}, {"word": "loyalty", "onset": 54.692, "offset": 55.242, "confidence": 0.97766}, {"word": "and", "onset": 55.306, "offset": 55.63, "confidence": 0.66}, {"word": "admiration.", "onset": 55.7, "offset": 56.458, "confidence": 0.80544}, {"word": "But", "onset": 56.554, "offset": 57.006, "confidence": 0.99513}, {"word": "the", "onset": 57.108, "offset": 57.326, "confidence": 1.0}, {"word": "point", "onset": 57.348, "offset": 57.534, "confidence": 1.0}, {"word": "is", "onset": 57.572, "offset": 57.726, "confidence": 0.99994}, {"word": "this.", "onset": 57.748, "offset": 58.32, "confidence": 0.99749}, {"word": "Under", "onset": 59.01, "offset": 59.374, "confidence": 0.99875}, {"word": "Donnie's", "onset": 59.412, "offset": 59.866, "confidence": 0.6322}, {"word": "leadership,", "onset": 59.898, "offset": 60.362, "confidence": 0.99974}, {"word": "along", "onset": 60.426, "offset": 60.654, "confidence": 0.99978}, {"word": "with", "onset": 60.692, "offset": 60.942, "confidence": 1.0}, {"word": "Nikki", "onset": 60.996, "offset": 61.386, "confidence": 0.68876}, {"word": "Koskov", "onset": 61.418, "offset": 62.106, "confidence": 0.50596}, {"word": "and", "onset": 62.138, "offset": 62.442, "confidence": 0.69}, {"word": "Robbie", "onset": 62.516, "offset": 62.846, "confidence": 0.97592}, {"word": "Feinberg", "onset": 62.878, "offset": 63.774, "confidence": 0.94849}, {"word": "moving", "onset": 63.902, "offset": 64.194, "confidence": 0.99903}, {"word": "into", "onset": 64.232, "offset": 64.434, "confidence": 0.99987}, {"word": "key", "onset": 64.472, "offset": 64.674, "confidence": 0.99926}, {"word": "management", "onset": 64.712, "offset": 65.134, "confidence": 0.99999}, {"word": "positions,", "onset": 65.182, "offset": 65.614, "confidence": 0.9988}, {"word": "this", "onset": 65.662, "offset": 65.826, "confidence": 0.99947}, {"word": "place", "onset": 65.848, "offset": 66.13, "confidence": 0.9998}, {"word": "really", "onset": 66.2, "offset": 66.434, "confidence": 0.99922}, {"word": "is", "onset": 66.472, "offset": 66.962, "confidence": 0.92722}, {"word": "going", "onset": 67.096, "offset": 67.346, "confidence": 0.54343}, {"word": "to", "onset": 67.368, "offset": 67.458, "confidence": 1.0}, {"word": "be", "onset": 67.464, "offset": 67.538, "confidence": 0.99967}, {"word": "better", "onset": 67.544, "offset": 67.714, "confidence": 0.99976}, {"word": "than", "onset": 67.752, "offset": 67.906, "confidence": 0.99991}, {"word": "ever.", "onset": 67.928, "offset": 68.114, "confidence": 0.9962}, {"word": "That", "onset": 68.152, "offset": 68.306, "confidence": 0.99471}, {"word": "I", "onset": 68.328, "offset": 68.466, "confidence": 1.0}, {"word": "promise", "onset": 68.488, "offset": 68.814, "confidence": 0.99877}, {"word": "you.", "onset": 68.862, "offset": 69.122, "confidence": 0.86}, {"word": "Okay?", "onset": 69.176, "offset": 69.78, "confidence": 0.69}, {"word": "This", "onset": 76.55, "offset": 76.866, "confidence": 0.99398}, {"word": "is", "onset": 76.888, "offset": 77.074, "confidence": 0.99871}, {"word": "Ellis", "onset": 77.112, "offset": 77.534, "confidence": 0.43669}, {"word": "island", "onset": 77.582, "offset": 77.934, "confidence": 0.99897}, {"word": "here,", "onset": 77.982, "offset": 78.29, "confidence": 0.47052}, {"word": "people.", "onset": 78.36, "offset": 78.834, "confidence": 0.94649}, {"word": "I", "onset": 78.952, "offset": 79.099, "confidence": 0.52}, {"word": "don't", "onset": 79.099, "offset": 79.218, "confidence": 0.51116}, {"word": "care", "onset": 79.234, "offset": 79.414, "confidence": 0.99362}, {"word": "who", "onset": 79.452, "offset": 79.606, "confidence": 0.9999}, {"word": "you", "onset": 79.628, "offset": 79.766, "confidence": 1.0}, {"word": "are,", "onset": 79.788, "offset": 80.07, "confidence": 0.99548}, {"word": "where", "onset": 80.14, "offset": 80.326, "confidence": 0.9998}, {"word": "you're", "onset": 80.348, "offset": 80.546, "confidence": 0.89434}, {"word": "from,", "onset": 80.578, "offset": 80.822, "confidence": 0.99877}, {"word": "whether", "onset": 80.876, "offset": 81.046, "confidence": 0.9987}, {"word": "your", "onset": 81.068, "offset": 81.206, "confidence": 0.99}, {"word": "relatives", "onset": 81.228, "offset": 81.666, "confidence": 0.99868}, {"word": "came", "onset": 81.698, "offset": 81.894, "confidence": 0.99996}, {"word": "over", "onset": 81.932, "offset": 82.086, "confidence": 1.0}, {"word": "on", "onset": 82.108, "offset": 82.39, "confidence": 0.71}, {"word": "the", "onset": 82.46, "offset": 82.598, "confidence": 0.96}, {"word": "fucking", "onset": 82.604, "offset": 82.866, "confidence": 0.98512}, {"word": "mayflower", "onset": 82.898, "offset": 83.586, "confidence": 0.74334}, {"word": "or", "onset": 83.618, "offset": 83.814, "confidence": 0.9}, {"word": "an", "onset": 83.852, "offset": 84.006, "confidence": 0.8}, {"word": "inner", "onset": 84.028, "offset": 84.258, "confidence": 0.91685}, {"word": "tube", "onset": 84.274, "offset": 84.466, "confidence": 0.98688}, {"word": "from", "onset": 84.498, "offset": 84.694, "confidence": 0.93136}, {"word": "Haiti,", "onset": 84.732, "offset": 85.51, "confidence": 0.48044}, {"word": "this", "onset": 86.01, "offset": 86.374, "confidence": 0.99956}, {"word": "right", "onset": 86.412, "offset": 86.662, "confidence": 0.97}, {"word": "here", "onset": 86.716, "offset": 86.886, "confidence": 0.99963}, {"word": "is", "onset": 86.908, "offset": 87.046, "confidence": 0.93165}, {"word": "the", "onset": 87.068, "offset": 87.206, "confidence": 1.0}, {"word": "land", "onset": 87.228, "offset": 87.366, "confidence": 0.99962}, {"word": "of", "onset": 87.388, "offset": 87.586, "confidence": 1.0}, {"word": "opportunity.", "onset": 87.628, "offset": 88.122, "confidence": 0.99223}, {"word": "Stratton", "onset": 88.256, "offset": 88.726, "confidence": 0.99689}, {"word": "Oakmont", "onset": 88.758, "offset": 89.526, "confidence": 0.72743}, {"word": "is", "onset": 89.638, "offset": 89.914, "confidence": 0.99998}, {"word": "America.", "onset": 89.952, "offset": 90.97, "confidence": 0.99809}, {"word": "All", "onset": 94.59, "offset": 94.906, "confidence": 1.0}, {"word": "of", "onset": 94.928, "offset": 95.018, "confidence": 1.0}, {"word": "you", "onset": 95.024, "offset": 95.146, "confidence": 1.0}, {"word": "know", "onset": 95.168, "offset": 95.306, "confidence": 0.99999}, {"word": "Kimmy", "onset": 95.328, "offset": 95.606, "confidence": 0.82909}, {"word": "Belzer,", "onset": 95.638, "offset": 96.086, "confidence": 0.60775}, {"word": "right?", "onset": 96.118, "offset": 96.41, "confidence": 1.0}, {"word": "Yes,", "onset": 96.48, "offset": 96.714, "confidence": 1.0}, {"word": "we", "onset": 96.752, "offset": 96.954, "confidence": 0.999}, {"word": "do.", "onset": 96.992, "offset": 97.626, "confidence": 0.9975}, {"word": "Fuck", "onset": 97.808, "offset": 98.246, "confidence": 0.99788}, {"word": "you.", "onset": 98.278, "offset": 98.86, "confidence": 1.0}, {"word": "Come", "onset": 99.39, "offset": 99.754, "confidence": 0.9987}, {"word": "on,", "onset": 99.792, "offset": 99.994, "confidence": 1.0}, {"word": "Kimmy.", "onset": 100.032, "offset": 100.47, "confidence": 0.57351}, {"word": "What", "onset": 100.55, "offset": 100.746, "confidence": 0.98741}, {"word": "you", "onset": 100.768, "offset": 100.954, "confidence": 0.99}, {"word": "probably", "onset": 100.992, "offset": 101.206, "confidence": 1.0}, {"word": "didn't", "onset": 101.248, "offset": 101.466, "confidence": 0.99973}, {"word": "know", "onset": 101.498, "offset": 101.694, "confidence": 0.99997}, {"word": "is", "onset": 101.732, "offset": 102.126, "confidence": 0.99938}, {"word": "Kimmy", "onset": 102.228, "offset": 102.666, "confidence": 0.99557}, {"word": "was", "onset": 102.698, "offset": 102.846, "confidence": 1.0}, {"word": "one", "onset": 102.868, "offset": 102.958, "confidence": 1.0}, {"word": "of", "onset": 102.964, "offset": 103.086, "confidence": 0.97}, {"word": "the", "onset": 103.108, "offset": 103.246, "confidence": 1.0}, {"word": "first", "onset": 103.268, "offset": 103.502, "confidence": 1.0}, {"word": "brokers", "onset": 103.556, "offset": 104.026, "confidence": 0.77313}, {"word": "here.", "onset": 104.058, "offset": 104.302, "confidence": 0.92192}, {"word": "One", "onset": 104.356, "offset": 104.478, "confidence": 1.0}, {"word": "of", "onset": 104.484, "offset": 104.606, "confidence": 1.0}, {"word": "Stratton's", "onset": 104.628, "offset": 105.146, "confidence": 0.99573}, {"word": "original", "onset": 105.178, "offset": 105.594, "confidence": 0.99899}, {"word": "20.", "onset": 105.642, "offset": 106.24, "confidence": 1.0}, {"word": "Now,", "onset": 107.09, "offset": 107.454, "confidence": 0.6}, {"word": "most", "onset": 107.492, "offset": 107.694, "confidence": 0.99995}, {"word": "of", "onset": 107.732, "offset": 107.838, "confidence": 1.0}, {"word": "you", "onset": 107.844, "offset": 107.966, "confidence": 1.0}, {"word": "met", "onset": 107.988, "offset": 108.222, "confidence": 0.99996}, {"word": "Kimmy,", "onset": 108.276, "offset": 108.634, "confidence": 0.62484}, {"word": "the", "onset": 108.682, "offset": 109.134, "confidence": 1.0}, {"word": "beautiful,", "onset": 109.252, "offset": 109.774, "confidence": 0.99998}, {"word": "sophisticated", "onset": 109.892, "offset": 110.682, "confidence": 0.73232}, {"word": "woman", "onset": 110.746, "offset": 111.018, "confidence": 0.99981}, {"word": "that", "onset": 111.034, "offset": 111.166, "confidence": 0.99919}, {"word": "she", "onset": 111.188, "offset": 111.326, "confidence": 0.99993}, {"word": "is", "onset": 111.348, "offset": 111.534, "confidence": 0.62977}, {"word": "today.", "onset": 111.572, "offset": 112.16, "confidence": 1.0}, {"word": "A", "onset": 112.53, "offset": 112.846, "confidence": 1.0}, {"word": "woman", "onset": 112.868, "offset": 113.098, "confidence": 0.99998}, {"word": "that", "onset": 113.114, "offset": 113.294, "confidence": 0.99995}, {"word": "wears", "onset": 113.332, "offset": 113.834, "confidence": 0.9098}, {"word": "$3,000", "onset": 113.962, "offset": 114.782, "confidence": 0.98}, {"word": "Armani", "onset": 114.836, "offset": 115.306, "confidence": 0.68054}, {"word": "suits,", "onset": 115.338, "offset": 116.11, "confidence": 0.99976}, {"word": "who", "onset": 117.41, "offset": 117.738, "confidence": 0.81349}, {"word": "drives", "onset": 117.764, "offset": 118.046, "confidence": 0.82682}, {"word": "a", "onset": 118.078, "offset": 118.178, "confidence": 1.0}, {"word": "brand", "onset": 118.184, "offset": 118.366, "confidence": 0.99995}, {"word": "new", "onset": 118.398, "offset": 118.546, "confidence": 1.0}, {"word": "Mercedesbenz,", "onset": 118.568, "offset": 119.89, "confidence": 0.78906}, {"word": "a", "onset": 120.79, "offset": 121.106, "confidence": 1.0}, {"word": "woman", "onset": 121.128, "offset": 121.406, "confidence": 0.99998}, {"word": "who", "onset": 121.438, "offset": 121.874, "confidence": 0.75484}, {"word": "spends", "onset": 121.992, "offset": 122.75, "confidence": 0.69562}, {"word": "her", "onset": 122.91, "offset": 123.234, "confidence": 0.88034}, {"word": "winters", "onset": 123.272, "offset": 123.582, "confidence": 0.51828}, {"word": "in", "onset": 123.646, "offset": 123.778, "confidence": 1.0}, {"word": "the", "onset": 123.784, "offset": 123.858, "confidence": 1.0}, {"word": "Bahamas", "onset": 123.864, "offset": 124.366, "confidence": 0.99858}, {"word": "and", "onset": 124.398, "offset": 124.546, "confidence": 1.0}, {"word": "her", "onset": 124.568, "offset": 124.706, "confidence": 0.98244}, {"word": "summers", "onset": 124.728, "offset": 125.018, "confidence": 0.99505}, {"word": "in", "onset": 125.054, "offset": 125.158, "confidence": 0.97}, {"word": "the", "onset": 125.164, "offset": 125.286, "confidence": 1.0}, {"word": "Hamptons.", "onset": 125.308, "offset": 126.07, "confidence": 0.95449}, {"word": "That's", "onset": 131.37, "offset": 131.778, "confidence": 0.96865}, {"word": "not", "onset": 131.794, "offset": 131.926, "confidence": 0.99978}, {"word": "the", "onset": 131.948, "offset": 132.038, "confidence": 1.0}, {"word": "Kimmy", "onset": 132.044, "offset": 132.338, "confidence": 0.94072}, {"word": "that", "onset": 132.354, "offset": 132.486, "confidence": 0.99924}, {"word": "I", "onset": 132.508, "offset": 132.646, "confidence": 1.0}, {"word": "met.", "onset": 132.668, "offset": 133.24, "confidence": 0.99966}, {"word": "The", "onset": 136.73, "offset": 137.046, "confidence": 0.99}, {"word": "Kimmy", "onset": 137.068, "offset": 137.378, "confidence": 0.93886}, {"word": "that", "onset": 137.394, "offset": 137.526, "confidence": 0.99959}, {"word": "I", "onset": 137.548, "offset": 137.686, "confidence": 1.0}, {"word": "met", "onset": 137.708, "offset": 137.894, "confidence": 0.99992}, {"word": "didn't", "onset": 137.932, "offset": 138.146, "confidence": 0.99979}, {"word": "have", "onset": 138.178, "offset": 138.326, "confidence": 0.99999}, {"word": "two", "onset": 138.348, "offset": 138.486, "confidence": 1.0}, {"word": "nickels", "onset": 138.508, "offset": 138.834, "confidence": 0.99739}, {"word": "to", "onset": 138.882, "offset": 139.01, "confidence": 0.84}, {"word": "rub", "onset": 139.02, "offset": 139.286, "confidence": 0.97433}, {"word": "together.", "onset": 139.318, "offset": 139.9, "confidence": 0.65135}, {"word": "She", "onset": 141.63, "offset": 141.946, "confidence": 0.99999}, {"word": "was", "onset": 141.968, "offset": 142.106, "confidence": 1.0}, {"word": "a", "onset": 142.128, "offset": 142.218, "confidence": 1.0}, {"word": "single", "onset": 142.224, "offset": 142.49, "confidence": 0.99999}, {"word": "mom", "onset": 142.56, "offset": 142.842, "confidence": 0.9999}, {"word": "on", "onset": 142.896, "offset": 143.066, "confidence": 1.0}, {"word": "the", "onset": 143.088, "offset": 143.178, "confidence": 1.0}, {"word": "balls", "onset": 143.184, "offset": 143.478, "confidence": 0.99967}, {"word": "of", "onset": 143.494, "offset": 143.626, "confidence": 1.0}, {"word": "her", "onset": 143.648, "offset": 143.786, "confidence": 0.90851}, {"word": "ass", "onset": 143.808, "offset": 143.994, "confidence": 0.9058}, {"word": "with", "onset": 144.032, "offset": 144.186, "confidence": 0.87}, {"word": "an", "onset": 144.208, "offset": 144.346, "confidence": 1.0}, {"word": "eight", "onset": 144.368, "offset": 144.506, "confidence": 1.0}, {"word": "year", "onset": 144.528, "offset": 144.666, "confidence": 0.92147}, {"word": "old", "onset": 144.688, "offset": 144.922, "confidence": 0.89765}, {"word": "son.", "onset": 144.976, "offset": 145.58, "confidence": 0.97837}, {"word": "Okay?", "onset": 146.03, "offset": 146.442, "confidence": 1.0}, {"word": "She", "onset": 146.496, "offset": 146.666, "confidence": 0.99997}, {"word": "was", "onset": 146.688, "offset": 146.826, "confidence": 1.0}, {"word": "three", "onset": 146.848, "offset": 147.034, "confidence": 1.0}, {"word": "months", "onset": 147.072, "offset": 147.37, "confidence": 0.99995}, {"word": "behind", "onset": 147.44, "offset": 147.722, "confidence": 1.0}, {"word": "on", "onset": 147.776, "offset": 147.946, "confidence": 1.0}, {"word": "her", "onset": 147.968, "offset": 148.106, "confidence": 0.98797}, {"word": "rent.", "onset": 148.128, "offset": 148.81, "confidence": 0.99961}, {"word": "And", "onset": 149.97, "offset": 150.286, "confidence": 0.99}, {"word": "when", "onset": 150.308, "offset": 150.446, "confidence": 0.99991}, {"word": "she", "onset": 150.468, "offset": 150.654, "confidence": 0.99995}, {"word": "came", "onset": 150.692, "offset": 150.846, "confidence": 0.99999}, {"word": "to", "onset": 150.868, "offset": 151.006, "confidence": 1.0}, {"word": "me", "onset": 151.028, "offset": 151.214, "confidence": 1.0}, {"word": "and", "onset": 151.252, "offset": 151.406, "confidence": 1.0}, {"word": "asked", "onset": 151.428, "offset": 151.614, "confidence": 0.99969}, {"word": "me", "onset": 151.652, "offset": 151.854, "confidence": 1.0}, {"word": "for", "onset": 151.892, "offset": 152.046, "confidence": 1.0}, {"word": "a", "onset": 152.068, "offset": 152.206, "confidence": 1.0}, {"word": "job,", "onset": 152.228, "offset": 152.8, "confidence": 0.99998}, {"word": "she", "onset": 153.73, "offset": 154.046, "confidence": 0.99991}, {"word": "asked", "onset": 154.068, "offset": 154.254, "confidence": 0.61129}, {"word": "for", "onset": 154.292, "offset": 154.446, "confidence": 0.82}, {"word": "a", "onset": 154.468, "offset": 154.654, "confidence": 0.92}, {"word": "$5,000", "onset": 154.692, "offset": 155.582, "confidence": 0.96}, {"word": "advance", "onset": 155.636, "offset": 156.042, "confidence": 0.99818}, {"word": "just", "onset": 156.106, "offset": 156.766, "confidence": 0.77293}, {"word": "so", "onset": 156.948, "offset": 157.294, "confidence": 0.99982}, {"word": "she", "onset": 157.332, "offset": 157.486, "confidence": 0.99988}, {"word": "could", "onset": 157.508, "offset": 157.646, "confidence": 0.99995}, {"word": "pay", "onset": 157.668, "offset": 157.854, "confidence": 0.99998}, {"word": "his", "onset": 157.892, "offset": 158.046, "confidence": 0.76225}, {"word": "son's", "onset": 158.068, "offset": 158.346, "confidence": 0.96416}, {"word": "tuition.", "onset": 158.378, "offset": 159.07, "confidence": 0.92133}, {"word": "What?", "onset": 163.81, "offset": 164.126, "confidence": 0.99972}, {"word": "I", "onset": 164.148, "offset": 164.286, "confidence": 0.91}, {"word": "do,", "onset": 164.308, "offset": 164.494, "confidence": 0.99996}, {"word": "Kimmy?", "onset": 164.532, "offset": 165.338, "confidence": 0.98051}, {"word": "Go", "onset": 165.514, "offset": 165.854, "confidence": 0.63626}, {"word": "on,", "onset": 165.892, "offset": 166.046, "confidence": 0.52}, {"word": "tell", "onset": 166.068, "offset": 166.254, "confidence": 0.41382}, {"word": "me.", "onset": 166.292, "offset": 166.88, "confidence": 0.52}, {"word": "You", "onset": 168.87, "offset": 169.282, "confidence": 0.55}, {"word": "wrote", "onset": 169.336, "offset": 169.614, "confidence": 0.99876}, {"word": "me", "onset": 169.662, "offset": 169.874, "confidence": 1.0}, {"word": "a", "onset": 169.912, "offset": 170.066, "confidence": 1.0}, {"word": "check", "onset": 170.088, "offset": 170.66, "confidence": 0.99665}, {"word": "for", "onset": 171.11, "offset": 171.522, "confidence": 0.99}, {"word": "$25,000.", "onset": 171.576, "offset": 173.06, "confidence": 0.99}, {"word": "That's", "onset": 174.55, "offset": 175.018, "confidence": 0.99947}, {"word": "right.", "onset": 175.054, "offset": 175.64, "confidence": 0.38}, {"word": "And", "onset": 180.65, "offset": 181.014, "confidence": 0.56}, {"word": "you", "onset": 181.052, "offset": 181.158, "confidence": 1.0}, {"word": "know", "onset": 181.164, "offset": 181.334, "confidence": 0.85943}, {"word": "why", "onset": 181.372, "offset": 181.526, "confidence": 0.98129}, {"word": "that", "onset": 181.548, "offset": 181.734, "confidence": 0.99975}, {"word": "is?", "onset": 181.772, "offset": 182.36, "confidence": 0.99538}, {"word": "It's", "onset": 185.93, "offset": 186.338, "confidence": 0.57164}, {"word": "because", "onset": 186.354, "offset": 186.582, "confidence": 0.99773}, {"word": "I", "onset": 186.636, "offset": 186.806, "confidence": 1.0}, {"word": "believed", "onset": 186.828, "offset": 187.186, "confidence": 0.99174}, {"word": "in", "onset": 187.218, "offset": 187.366, "confidence": 1.0}, {"word": "you.", "onset": 187.388, "offset": 187.96, "confidence": 1.0}, {"word": "It's", "onset": 189.87, "offset": 190.246, "confidence": 0.87913}, {"word": "because", "onset": 190.278, "offset": 190.522, "confidence": 0.99933}, {"word": "I", "onset": 190.576, "offset": 190.746, "confidence": 1.0}, {"word": "believed", "onset": 190.768, "offset": 191.078, "confidence": 0.99452}, {"word": "in", "onset": 191.094, "offset": 191.226, "confidence": 1.0}, {"word": "you,", "onset": 191.248, "offset": 191.434, "confidence": 1.0}, {"word": "Kimmy,", "onset": 191.472, "offset": 192.25, "confidence": 0.9814}, {"word": "just", "onset": 193.23, "offset": 193.642, "confidence": 0.99948}, {"word": "like", "onset": 193.696, "offset": 193.914, "confidence": 0.9996}, {"word": "I", "onset": 193.952, "offset": 194.106, "confidence": 1.0}, {"word": "believe", "onset": 194.128, "offset": 194.314, "confidence": 0.99987}, {"word": "in", "onset": 194.352, "offset": 194.554, "confidence": 1.0}, {"word": "each", "onset": 194.592, "offset": 194.842, "confidence": 0.9999}, {"word": "and", "onset": 194.896, "offset": 195.162, "confidence": 1.0}, {"word": "every", "onset": 195.216, "offset": 195.53, "confidence": 0.99978}, {"word": "one", "onset": 195.6, "offset": 195.834, "confidence": 1.0}, {"word": "of", "onset": 195.872, "offset": 196.074, "confidence": 0.99}, {"word": "you", "onset": 196.112, "offset": 196.362, "confidence": 1.0}, {"word": "here", "onset": 196.416, "offset": 196.682, "confidence": 0.9997}, {"word": "today.", "onset": 196.736, "offset": 197.146, "confidence": 0.99}, {"word": "I", "onset": 197.248, "offset": 197.514, "confidence": 1.0}, {"word": "fucking", "onset": 197.552, "offset": 198.022, "confidence": 0.99398}, {"word": "love", "onset": 198.086, "offset": 198.314, "confidence": 0.99915}, {"word": "you,", "onset": 198.352, "offset": 198.506, "confidence": 0.75}, {"word": "Jordan.", "onset": 198.528, "offset": 199.27, "confidence": 0.94604}, {"word": "I", "onset": 199.43, "offset": 199.706, "confidence": 1.0}, {"word": "fucking", "onset": 199.728, "offset": 200.054, "confidence": 0.99178}, {"word": "love", "onset": 200.102, "offset": 200.314, "confidence": 0.99971}, {"word": "you.", "onset": 200.352, "offset": 200.554, "confidence": 1.0}, {"word": "I", "onset": 200.592, "offset": 200.746, "confidence": 0.99}, {"word": "love", "onset": 200.768, "offset": 200.906, "confidence": 0.99951}, {"word": "you.", "onset": 200.928, "offset": 201.114, "confidence": 0.99}, {"word": "I", "onset": 201.152, "offset": 201.306, "confidence": 0.99}, {"word": "fucking", "onset": 201.328, "offset": 201.606, "confidence": 0.99129}, {"word": "love", "onset": 201.638, "offset": 201.834, "confidence": 0.99879}, {"word": "you,", "onset": 201.872, "offset": 202.074, "confidence": 0.95}, {"word": "too.", "onset": 202.112, "offset": 202.602, "confidence": 0.95}, {"word": "I", "onset": 202.736, "offset": 202.998, "confidence": 0.66}, {"word": "fucking", "onset": 203.024, "offset": 203.466, "confidence": 0.58874}, {"word": "love", "onset": 203.498, "offset": 203.646, "confidence": 0.7589}, {"word": "you,", "onset": 203.668, "offset": 203.854, "confidence": 0.58}, {"word": "too.", "onset": 203.892, "offset": 204.48, "confidence": 0.97}, {"word": "And", "onset": 207.09, "offset": 207.406, "confidence": 1.0}, {"word": "I", "onset": 207.428, "offset": 207.614, "confidence": 0.99}, {"word": "love", "onset": 207.652, "offset": 207.854, "confidence": 0.99986}, {"word": "all", "onset": 207.892, "offset": 208.094, "confidence": 1.0}, {"word": "of", "onset": 208.132, "offset": 208.286, "confidence": 0.98}, {"word": "you.", "onset": 208.308, "offset": 208.88, "confidence": 0.99}, {"word": "I", "onset": 209.73, "offset": 210.046, "confidence": 0.99}, {"word": "love", "onset": 210.068, "offset": 210.254, "confidence": 0.9999}, {"word": "all", "onset": 210.292, "offset": 210.494, "confidence": 1.0}, {"word": "of", "onset": 210.532, "offset": 210.686, "confidence": 0.96}, {"word": "you", "onset": 210.708, "offset": 210.846, "confidence": 0.99}, {"word": "from", "onset": 210.868, "offset": 211.054, "confidence": 0.61864}, {"word": "the", "onset": 211.092, "offset": 211.246, "confidence": 0.99}, {"word": "bottom", "onset": 211.268, "offset": 211.454, "confidence": 0.99781}, {"word": "of", "onset": 211.492, "offset": 211.598, "confidence": 0.64}, {"word": "my", "onset": 211.604, "offset": 211.726, "confidence": 1.0}, {"word": "arm.", "onset": 211.748, "offset": 212.43, "confidence": 0.54652}, {"word": "I", "onset": 213.09, "offset": 213.454, "confidence": 0.98}, {"word": "mean", "onset": 213.492, "offset": 213.694, "confidence": 0.9997}, {"word": "that.", "onset": 213.732, "offset": 214.32, "confidence": 0.92074}, {"word": "Because", "onset": 225.29, "offset": 226.04, "confidence": 0.98073}, {"word": "for", "onset": 227.93, "offset": 228.294, "confidence": 1.0}, {"word": "years,", "onset": 228.332, "offset": 228.534, "confidence": 0.99998}, {"word": "I've", "onset": 228.572, "offset": 228.786, "confidence": 0.94279}, {"word": "been", "onset": 228.818, "offset": 228.966, "confidence": 1.0}, {"word": "telling", "onset": 228.988, "offset": 229.266, "confidence": 0.99999}, {"word": "you", "onset": 229.298, "offset": 229.446, "confidence": 1.0}, {"word": "guys", "onset": 229.468, "offset": 229.942, "confidence": 0.99999}, {"word": "never", "onset": 230.076, "offset": 230.374, "confidence": 0.99994}, {"word": "to", "onset": 230.412, "offset": 230.518, "confidence": 1.0}, {"word": "take", "onset": 230.524, "offset": 230.694, "confidence": 0.99994}, {"word": "no", "onset": 230.732, "offset": 230.934, "confidence": 0.96}, {"word": "for", "onset": 230.972, "offset": 231.078, "confidence": 1.0}, {"word": "an", "onset": 231.084, "offset": 231.206, "confidence": 1.0}, {"word": "answer,", "onset": 231.228, "offset": 231.558, "confidence": 0.99862}, {"word": "right?", "onset": 231.644, "offset": 232.28, "confidence": 1.0}, {"word": "To", "onset": 232.89, "offset": 233.206, "confidence": 1.0}, {"word": "keep", "onset": 233.228, "offset": 233.462, "confidence": 0.99999}, {"word": "pushing,", "onset": 233.516, "offset": 233.906, "confidence": 0.99964}, {"word": "to", "onset": 233.938, "offset": 234.326, "confidence": 0.72}, {"word": "never", "onset": 234.428, "offset": 234.742, "confidence": 0.99925}, {"word": "hang", "onset": 234.796, "offset": 235.058, "confidence": 0.87231}, {"word": "up", "onset": 235.074, "offset": 235.254, "confidence": 0.8}, {"word": "the", "onset": 235.292, "offset": 235.494, "confidence": 1.0}, {"word": "phone", "onset": 235.532, "offset": 236.166, "confidence": 0.99998}, {"word": "until", "onset": 236.348, "offset": 236.79, "confidence": 0.99994}, {"word": "you", "onset": 236.86, "offset": 237.19, "confidence": 1.0}, {"word": "get", "onset": 237.26, "offset": 237.494, "confidence": 0.99999}, {"word": "what", "onset": 237.532, "offset": 237.686, "confidence": 0.99999}, {"word": "you", "onset": 237.708, "offset": 237.894, "confidence": 1.0}, {"word": "want.", "onset": 237.932, "offset": 238.52, "confidence": 0.99983}, {"word": "Because", "onset": 239.61, "offset": 240.022, "confidence": 0.99991}, {"word": "you", "onset": 240.076, "offset": 240.246, "confidence": 1.0}, {"word": "all", "onset": 240.268, "offset": 240.454, "confidence": 1.0}, {"word": "deserve", "onset": 240.492, "offset": 240.866, "confidence": 0.99675}, {"word": "it.", "onset": 240.898, "offset": 241.48, "confidence": 0.99982}, {"word": "This", "onset": 243.47, "offset": 243.834, "confidence": 0.99893}, {"word": "fucking", "onset": 243.872, "offset": 244.166, "confidence": 0.9984}, {"word": "deal", "onset": 244.198, "offset": 244.394, "confidence": 1.0}, {"word": "that", "onset": 244.432, "offset": 244.538, "confidence": 0.99999}, {"word": "I'm", "onset": 244.544, "offset": 244.726, "confidence": 0.99892}, {"word": "about", "onset": 244.758, "offset": 244.906, "confidence": 0.99997}, {"word": "to", "onset": 244.928, "offset": 245.114, "confidence": 1.0}, {"word": "sign,", "onset": 245.152, "offset": 245.74, "confidence": 0.99993}, {"word": "barring", "onset": 246.99, "offset": 247.558, "confidence": 0.93561}, {"word": "me", "onset": 247.574, "offset": 247.706, "confidence": 1.0}, {"word": "from", "onset": 247.728, "offset": 247.866, "confidence": 0.99995}, {"word": "the", "onset": 247.888, "offset": 248.026, "confidence": 1.0}, {"word": "securities", "onset": 248.048, "offset": 248.55, "confidence": 0.80876}, {"word": "industry,", "onset": 248.63, "offset": 249.142, "confidence": 0.99999}, {"word": "barring", "onset": 249.206, "offset": 249.606, "confidence": 0.97652}, {"word": "me", "onset": 249.638, "offset": 249.786, "confidence": 1.0}, {"word": "from", "onset": 249.808, "offset": 250.054, "confidence": 0.99994}, {"word": "Stratton,", "onset": 250.112, "offset": 250.91, "confidence": 0.77235}, {"word": "my", "onset": 252.13, "offset": 252.494, "confidence": 1.0}, {"word": "home.", "onset": 252.532, "offset": 253.12, "confidence": 0.93387}, {"word": "The", "onset": 256.37, "offset": 256.734, "confidence": 0.99}, {"word": "fuck", "onset": 256.772, "offset": 256.986, "confidence": 0.99858}, {"word": "is", "onset": 257.018, "offset": 257.214, "confidence": 0.99976}, {"word": "that?", "onset": 257.252, "offset": 257.84, "confidence": 0.76879}, {"word": "I'll", "onset": 259.57, "offset": 259.946, "confidence": 0.78236}, {"word": "tell", "onset": 259.978, "offset": 260.078, "confidence": 0.99996}, {"word": "you", "onset": 260.084, "offset": 260.206, "confidence": 0.95}, {"word": "what", "onset": 260.228, "offset": 260.366, "confidence": 0.99999}, {"word": "it", "onset": 260.388, "offset": 260.478, "confidence": 0.99967}, {"word": "is?", "onset": 260.484, "offset": 261.04, "confidence": 0.95575}, {"word": "It's", "onset": 262.53, "offset": 262.954, "confidence": 0.96743}, {"word": "me", "onset": 263.002, "offset": 263.166, "confidence": 1.0}, {"word": "taking", "onset": 263.188, "offset": 263.47, "confidence": 0.63704}, {"word": "no", "onset": 263.54, "offset": 263.822, "confidence": 1.0}, {"word": "for", "onset": 263.876, "offset": 264.046, "confidence": 1.0}, {"word": "an", "onset": 264.068, "offset": 264.206, "confidence": 1.0}, {"word": "answer.", "onset": 264.228, "offset": 264.8, "confidence": 0.86532}, {"word": "It's", "onset": 267.01, "offset": 267.87, "confidence": 0.91284}, {"word": "them", "onset": 268.45, "offset": 268.814, "confidence": 0.99948}, {"word": "selling", "onset": 268.852, "offset": 269.194, "confidence": 0.94084}, {"word": "me,", "onset": 269.242, "offset": 269.406, "confidence": 1.0}, {"word": "not", "onset": 269.428, "offset": 269.566, "confidence": 0.99995}, {"word": "the", "onset": 269.588, "offset": 269.726, "confidence": 0.53}, {"word": "other", "onset": 269.748, "offset": 269.886, "confidence": 0.99999}, {"word": "way", "onset": 269.908, "offset": 270.094, "confidence": 1.0}, {"word": "around.", "onset": 270.132, "offset": 270.72, "confidence": 0.99478}, {"word": "It's", "onset": 272.29, "offset": 272.666, "confidence": 0.99979}, {"word": "me", "onset": 272.698, "offset": 272.846, "confidence": 0.98}, {"word": "being", "onset": 272.868, "offset": 273.054, "confidence": 0.99991}, {"word": "a", "onset": 273.092, "offset": 273.198, "confidence": 1.0}, {"word": "hypocrite,", "onset": 273.204, "offset": 273.706, "confidence": 0.99512}, {"word": "is", "onset": 273.738, "offset": 273.838, "confidence": 0.9996}, {"word": "what", "onset": 273.844, "offset": 273.966, "confidence": 0.99984}, {"word": "it", "onset": 273.988, "offset": 274.126, "confidence": 0.9997}, {"word": "is.", "onset": 274.148, "offset": 274.72, "confidence": 0.99042}, {"word": "It.", "onset": 287.87, "offset": 288.618, "confidence": 0.53972}, {"word": "You", "onset": 288.784, "offset": 289.066, "confidence": 0.99}, {"word": "know", "onset": 289.088, "offset": 289.226, "confidence": 0.99997}, {"word": "what?", "onset": 289.248, "offset": 289.82, "confidence": 0.99945}, {"word": "I'm", "onset": 294.11, "offset": 294.518, "confidence": 0.71532}, {"word": "not", "onset": 294.534, "offset": 294.714, "confidence": 0.99939}, {"word": "leaving.", "onset": 294.752, "offset": 295.37, "confidence": 0.99924}, {"word": "I'm", "onset": 298.11, "offset": 298.486, "confidence": 0.99024}, {"word": "not", "onset": 298.518, "offset": 298.714, "confidence": 0.99997}, {"word": "leaving.", "onset": 298.752, "offset": 299.37, "confidence": 0.9998}, {"word": "I'm", "onset": 302.05, "offset": 302.378, "confidence": 0.67262}, {"word": "not", "onset": 302.394, "offset": 302.526, "confidence": 0.96263}, {"word": "fucking", "onset": 302.548, "offset": 302.858, "confidence": 0.65703}, {"word": "leaving", "onset": 302.874, "offset": 303.47, "confidence": 0.98143}, {"word": "you.", "onset": 308.29, "offset": 309.04, "confidence": 0.18}, {"word": "The", "onset": 312.13, "offset": 312.494, "confidence": 0.93}, {"word": "show", "onset": 312.532, "offset": 312.782, "confidence": 0.99979}, {"word": "goes", "onset": 312.836, "offset": 313.102, "confidence": 0.99954}, {"word": "on.", "onset": 313.156, "offset": 313.76, "confidence": 0.99}, {"word": "This", "onset": 316.13, "offset": 316.446, "confidence": 0.9999}, {"word": "is", "onset": 316.468, "offset": 316.702, "confidence": 0.98087}, {"word": "my", "onset": 316.756, "offset": 316.974, "confidence": 1.0}, {"word": "home.", "onset": 317.012, "offset": 317.598, "confidence": 0.7686}, {"word": "They're", "onset": 317.764, "offset": 318.106, "confidence": 0.94768}, {"word": "gonna", "onset": 318.138, "offset": 318.394, "confidence": 0.81937}, {"word": "need", "onset": 318.452, "offset": 318.674, "confidence": 0.99991}, {"word": "a", "onset": 318.712, "offset": 318.866, "confidence": 1.0}, {"word": "fucking", "onset": 318.888, "offset": 319.294, "confidence": 0.99402}, {"word": "wrecking", "onset": 319.342, "offset": 319.854, "confidence": 0.57201}, {"word": "ball", "onset": 319.902, "offset": 320.446, "confidence": 0.99493}, {"word": "to", "onset": 320.558, "offset": 320.882, "confidence": 1.0}, {"word": "take", "onset": 320.936, "offset": 321.202, "confidence": 0.99354}, {"word": "me", "onset": 321.256, "offset": 321.57, "confidence": 1.0}, {"word": "out", "onset": 321.64, "offset": 321.826, "confidence": 0.99979}, {"word": "of", "onset": 321.848, "offset": 322.034, "confidence": 0.77}, {"word": "here.", "onset": 322.072, "offset": 322.66, "confidence": 0.99674}, {"word": "They're", "onset": 324.39, "offset": 324.766, "confidence": 0.55804}, {"word": "going", "onset": 324.798, "offset": 324.898, "confidence": 0.98127}, {"word": "to", "onset": 324.904, "offset": 325.038, "confidence": 0.57}, {"word": "need", "onset": 325.064, "offset": 325.254, "confidence": 0.98996}, {"word": "to", "onset": 325.292, "offset": 325.446, "confidence": 0.99}, {"word": "send", "onset": 325.468, "offset": 325.654, "confidence": 0.9723}, {"word": "you", "onset": 325.692, "offset": 325.894, "confidence": 0.56}, {"word": "the", "onset": 325.932, "offset": 326.134, "confidence": 1.0}, {"word": "national", "onset": 326.172, "offset": 326.626, "confidence": 0.64152}, {"word": "God", "onset": 326.738, "offset": 327.062, "confidence": 0.75724}, {"word": "of", "onset": 327.116, "offset": 327.334, "confidence": 0.59}, {"word": "fucking", "onset": 327.372, "offset": 327.794, "confidence": 0.99011}, {"word": "SWAT", "onset": 327.842, "offset": 328.226, "confidence": 0.92083}, {"word": "team.", "onset": 328.258, "offset": 328.742, "confidence": 0.9943}, {"word": "Because", "onset": 328.876, "offset": 329.174, "confidence": 0.87938}, {"word": "I", "onset": 329.212, "offset": 329.366, "confidence": 1.0}, {"word": "ain't", "onset": 329.388, "offset": 329.622, "confidence": 0.43306}, {"word": "going", "onset": 329.676, "offset": 329.99, "confidence": 0.99412}, {"word": "nowhere.", "onset": 330.06, "offset": 330.79, "confidence": 0.74938}, {"word": "Feet", "onset": 399.97, "offset": 400.394, "confidence": 0.81}, {"word": "to", "onset": 400.442, "offset": 400.606, "confidence": 0.98}, {"word": "the", "onset": 400.628, "offset": 400.814, "confidence": 0.75}, {"word": "rocket", "onset": 400.852, "offset": 401.71, "confidence": 0.41911}, {"word": "of", "onset": 403.01, "offset": 403.374, "confidence": 0.78}, {"word": "inspector", "onset": 403.412, "offset": 404.042, "confidence": 0.70773}, {"word": "seven.", "onset": 404.106, "offset": 404.72, "confidence": 0.98}, {"word": "One", "onset": 405.17, "offset": 405.822, "confidence": 0.73}, {"word": "step", "onset": 405.956, "offset": 406.398, "confidence": 0.78673}, {"word": "beyond.", "onset": 406.484, "offset": 407.23, "confidence": 0.56651}, {"word": "It", "onset": 412.61, "offset": 412.878, "confidence": 0.98228}, {"word": "was", "onset": 412.884, "offset": 413.054, "confidence": 1.0}, {"word": "our", "onset": 413.092, "offset": 413.342, "confidence": 0.93}, {"word": "time", "onset": 413.396, "offset": 413.662, "confidence": 0.99984}, {"word": "to", "onset": 413.716, "offset": 413.934, "confidence": 0.99}, {"word": "party", "onset": 413.972, "offset": 414.442, "confidence": 0.53261}, {"word": "big.", "onset": 414.506, "offset": 414.89, "confidence": 0.99926}, {"word": "And", "onset": 414.98, "offset": 415.234, "confidence": 1.0}, {"word": "just", "onset": 415.272, "offset": 415.474, "confidence": 0.99968}, {"word": "as", "onset": 415.512, "offset": 415.666, "confidence": 0.98994}, {"word": "Brad", "onset": 415.688, "offset": 415.966, "confidence": 0.99945}, {"word": "was", "onset": 415.998, "offset": 416.194, "confidence": 1.0}, {"word": "released", "onset": 416.232, "offset": 416.494, "confidence": 0.7851}, {"word": "from", "onset": 416.542, "offset": 416.706, "confidence": 0.99996}, {"word": "jail,", "onset": 416.728, "offset": 417.054, "confidence": 0.9996}, {"word": "too.", "onset": 417.102, "offset": 417.7, "confidence": 1.0}, {"word": "I", "onset": 418.39, "offset": 418.754, "confidence": 1.0}, {"word": "apologized,", "onset": 418.792, "offset": 419.694, "confidence": 0.9602}, {"word": "even", "onset": 419.822, "offset": 420.114, "confidence": 0.99996}, {"word": "offered", "onset": 420.152, "offset": 420.478, "confidence": 0.99939}, {"word": "to", "onset": 420.494, "offset": 420.626, "confidence": 1.0}, {"word": "pay", "onset": 420.648, "offset": 420.786, "confidence": 0.99948}, {"word": "him", "onset": 420.808, "offset": 420.898, "confidence": 0.99976}, {"word": "for", "onset": 420.904, "offset": 421.026, "confidence": 0.99}, {"word": "his", "onset": 421.048, "offset": 421.186, "confidence": 0.99996}, {"word": "time", "onset": 421.208, "offset": 421.394, "confidence": 0.99997}, {"word": "in", "onset": 421.432, "offset": 421.538, "confidence": 1.0}, {"word": "the", "onset": 421.544, "offset": 421.666, "confidence": 0.94}, {"word": "can.", "onset": 421.688, "offset": 422.26, "confidence": 0.75946}, {"word": "But", "onset": 422.87, "offset": 423.186, "confidence": 0.9996}, {"word": "he", "onset": 423.208, "offset": 423.346, "confidence": 0.6959}, {"word": "said", "onset": 423.368, "offset": 423.602, "confidence": 0.98899}, {"word": "no,", "onset": 423.656, "offset": 423.922, "confidence": 1.0}, {"word": "that", "onset": 423.976, "offset": 424.146, "confidence": 0.89941}, {"word": "he", "onset": 424.168, "offset": 424.306, "confidence": 0.9983}, {"word": "was", "onset": 424.328, "offset": 424.514, "confidence": 1.0}, {"word": "out.", "onset": 424.552, "offset": 425.054, "confidence": 0.99991}, {"word": "He", "onset": 425.192, "offset": 425.446, "confidence": 0.99495}, {"word": "didn't", "onset": 425.468, "offset": 425.618, "confidence": 0.99983}, {"word": "want", "onset": 425.634, "offset": 425.814, "confidence": 0.99997}, {"word": "any", "onset": 425.852, "offset": 426.006, "confidence": 0.99993}, {"word": "part", "onset": 426.028, "offset": 426.214, "confidence": 0.9998}, {"word": "of", "onset": 426.252, "offset": 426.406, "confidence": 1.0}, {"word": "us.", "onset": 426.428, "offset": 426.998, "confidence": 1.0}, {"word": "Sad", "onset": 427.164, "offset": 427.586, "confidence": 0.99989}, {"word": "thing", "onset": 427.618, "offset": 427.862, "confidence": 0.99998}, {"word": "was,", "onset": 427.916, "offset": 428.566, "confidence": 1.0}, {"word": "two", "onset": 428.748, "offset": 429.094, "confidence": 1.0}, {"word": "years", "onset": 429.132, "offset": 429.382, "confidence": 0.99994}, {"word": "later", "onset": 429.436, "offset": 430.086, "confidence": 0.90857}, {"word": "he", "onset": 430.268, "offset": 430.566, "confidence": 0.9231}, {"word": "was", "onset": 430.588, "offset": 430.774, "confidence": 0.63}, {"word": "dead.", "onset": 430.812, "offset": 431.51, "confidence": 0.99905}, {"word": "Massive", "onset": 432.25, "offset": 432.754, "confidence": 0.99814}, {"word": "heart", "onset": 432.802, "offset": 433.014, "confidence": 0.99997}, {"word": "attack.", "onset": 433.052, "offset": 433.446, "confidence": 0.99968}, {"word": "35.", "onset": 433.548, "offset": 434.6, "confidence": 1.0}, {"word": "Same", "onset": 435.37, "offset": 435.782, "confidence": 0.51551}, {"word": "age", "onset": 435.836, "offset": 436.054, "confidence": 0.99993}, {"word": "Mozart", "onset": 436.092, "offset": 436.642, "confidence": 0.84492}, {"word": "died.", "onset": 436.706, "offset": 437.35, "confidence": 0.96426}, {"word": "Not", "onset": 437.79, "offset": 438.154, "confidence": 0.93586}, {"word": "that", "onset": 438.192, "offset": 438.346, "confidence": 0.99943}, {"word": "they", "onset": 438.368, "offset": 438.698, "confidence": 0.73108}, {"word": "have", "onset": 438.784, "offset": 438.986, "confidence": 0.99866}, {"word": "a", "onset": 439.008, "offset": 439.146, "confidence": 1.0}, {"word": "hell", "onset": 439.168, "offset": 439.306, "confidence": 0.99828}, {"word": "of", "onset": 439.328, "offset": 439.418, "confidence": 1.0}, {"word": "a", "onset": 439.424, "offset": 439.498, "confidence": 1.0}, {"word": "lot", "onset": 439.504, "offset": 439.674, "confidence": 0.99936}, {"word": "in", "onset": 439.712, "offset": 439.866, "confidence": 1.0}, {"word": "common,", "onset": 439.888, "offset": 440.17, "confidence": 0.99994}, {"word": "but.", "onset": 440.24, "offset": 440.954, "confidence": 0.98037}, {"word": "Anyway,", "onset": 441.152, "offset": 441.562, "confidence": 0.99895}, {"word": "I", "onset": 441.616, "offset": 441.738, "confidence": 1.0}, {"word": "don't", "onset": 441.744, "offset": 441.818, "confidence": 0.97504}, {"word": "know", "onset": 441.824, "offset": 441.898, "confidence": 0.99965}, {"word": "why", "onset": 441.904, "offset": 442.026, "confidence": 0.99456}, {"word": "that", "onset": 442.048, "offset": 442.186, "confidence": 0.95636}, {"word": "came", "onset": 442.208, "offset": 442.346, "confidence": 0.99988}, {"word": "to", "onset": 442.368, "offset": 442.506, "confidence": 1.0}, {"word": "mind.", "onset": 442.528, "offset": 443.1, "confidence": 0.9989}, {"word": "Within", "onset": 445.95, "offset": 446.41, "confidence": 0.99949}, {"word": "days,", "onset": 446.48, "offset": 446.954, "confidence": 0.99932}, {"word": "subpoenas", "onset": 447.072, "offset": 447.734, "confidence": 0.62327}, {"word": "started", "onset": 447.782, "offset": 448.138, "confidence": 1.0}, {"word": "flying.", "onset": 448.224, "offset": 449.05, "confidence": 0.99773}, {"word": "Notices", "onset": 449.39, "offset": 449.954, "confidence": 0.99925}, {"word": "to", "onset": 450.022, "offset": 450.206, "confidence": 0.98}, {"word": "produce", "onset": 450.228, "offset": 450.554, "confidence": 0.99892}, {"word": "documents,", "onset": 450.602, "offset": 451.258, "confidence": 0.9821}, {"word": "depositions,", "onset": 451.354, "offset": 452.074, "confidence": 0.85725}, {"word": "you", "onset": 452.122, "offset": 452.286, "confidence": 1.0}, {"word": "name", "onset": 452.308, "offset": 452.494, "confidence": 1.0}, {"word": "it.", "onset": 452.532, "offset": 452.782, "confidence": 0.98659}, {"word": "Donnie", "onset": 452.836, "offset": 453.226, "confidence": 0.69389}, {"word": "couldn't", "onset": 453.258, "offset": 453.466, "confidence": 0.97953}, {"word": "drink", "onset": 453.498, "offset": 453.706, "confidence": 0.99988}, {"word": "water", "onset": 453.738, "offset": 453.982, "confidence": 0.99967}, {"word": "fast", "onset": 454.036, "offset": 454.302, "confidence": 0.9659}, {"word": "enough.", "onset": 454.356, "offset": 454.67, "confidence": 0.85681}, {"word": "United", "onset": 454.74, "offset": 454.974, "confidence": 0.99}, {"word": "States", "onset": 455.012, "offset": 455.262, "confidence": 0.89}, {"word": "government", "onset": 455.316, "offset": 455.534, "confidence": 0.97395}, {"word": "wants", "onset": 455.572, "offset": 455.726, "confidence": 0.99661}, {"word": "to", "onset": 455.748, "offset": 455.838, "confidence": 1.0}, {"word": "get", "onset": 455.844, "offset": 455.966, "confidence": 0.90232}, {"word": "me", "onset": 455.988, "offset": 456.126, "confidence": 0.99}, {"word": "a", "onset": 456.148, "offset": 456.238, "confidence": 0.95}, {"word": "subpoena?", "onset": 456.244, "offset": 456.89, "confidence": 0.76314}, {"word": "Here's", "onset": 456.97, "offset": 457.178, "confidence": 0.99774}, {"word": "what", "onset": 457.194, "offset": 457.326, "confidence": 0.99651}, {"word": "we", "onset": 457.348, "offset": 457.438, "confidence": 0.99884}, {"word": "do", "onset": 457.444, "offset": 457.566, "confidence": 0.99522}, {"word": "with", "onset": 457.588, "offset": 457.678, "confidence": 0.95}, {"word": "subpoenas", "onset": 457.684, "offset": 458.074, "confidence": 0.68832}, {"word": "in", "onset": 458.122, "offset": 458.238, "confidence": 0.29}, {"word": "Stratton.", "onset": 458.244, "offset": 458.99, "confidence": 0.23537}, {"word": "Fuck", "onset": 466.45, "offset": 466.874, "confidence": 0.57225}, {"word": "you,", "onset": 466.922, "offset": 467.182, "confidence": 0.99}, {"word": "USA.", "onset": 467.236, "offset": 467.93, "confidence": 0.86063}, {"word": "Fuck", "onset": 468.01, "offset": 468.314, "confidence": 0.74736}, {"word": "you.", "onset": 468.362, "offset": 469.054, "confidence": 0.99}, {"word": "Fuck", "onset": 469.252, "offset": 469.754, "confidence": 0.97574}, {"word": "you.", "onset": 469.802, "offset": 470.206, "confidence": 0.99}, {"word": "Fuck", "onset": 470.308, "offset": 470.714, "confidence": 0.9835}, {"word": "you.", "onset": 470.762, "offset": 471.118, "confidence": 0.98}, {"word": "Fuck", "onset": 471.204, "offset": 471.594, "confidence": 0.97217}, {"word": "you.", "onset": 471.642, "offset": 471.998, "confidence": 0.99}, {"word": "Fuck", "onset": 472.084, "offset": 472.474, "confidence": 0.97741}, {"word": "you.", "onset": 472.522, "offset": 472.83, "confidence": 0.98}, {"word": "Fuck", "onset": 472.9, "offset": 473.194, "confidence": 0.90898}, {"word": "you.", "onset": 473.242, "offset": 473.55, "confidence": 0.97}, {"word": "Fuck", "onset": 473.62, "offset": 473.914, "confidence": 0.86744}, {"word": "you.", "onset": 473.962, "offset": 474.56, "confidence": 0.96}, {"word": "Jordan", "onset": 480.57, "offset": 481.522, "confidence": 0.63452}, {"word": "Belfort.", "onset": 481.666, "offset": 482.562, "confidence": 0.981}, {"word": "Olden,", "onset": 482.706, "offset": 483.522, "confidence": 0.35997}, {"word": "that's", "onset": 483.666, "offset": 483.986, "confidence": 0.63969}, {"word": "a", "onset": 484.018, "offset": 484.118, "confidence": 1.0}, {"word": "nice", "onset": 484.124, "offset": 484.342, "confidence": 0.99989}, {"word": "name.", "onset": 484.396, "offset": 484.758, "confidence": 1.0}, {"word": "Thank", "onset": 484.844, "offset": 485.094, "confidence": 0.99978}, {"word": "you", "onset": 485.132, "offset": 485.286, "confidence": 1.0}, {"word": "very", "onset": 485.308, "offset": 485.446, "confidence": 0.99969}, {"word": "much", "onset": 485.468, "offset": 485.606, "confidence": 0.99991}, {"word": "for", "onset": 485.628, "offset": 485.766, "confidence": 1.0}, {"word": "that.", "onset": 485.788, "offset": 485.974, "confidence": 0.99834}, {"word": "What", "onset": 486.012, "offset": 486.166, "confidence": 0.99803}, {"word": "kind", "onset": 486.188, "offset": 486.326, "confidence": 0.9997}, {"word": "of", "onset": 486.348, "offset": 486.438, "confidence": 1.0}, {"word": "name", "onset": 486.444, "offset": 486.614, "confidence": 1.0}, {"word": "is", "onset": 486.652, "offset": 486.806, "confidence": 0.99986}, {"word": "that?", "onset": 486.828, "offset": 487.254, "confidence": 0.99782}, {"word": "That", "onset": 487.372, "offset": 487.654, "confidence": 0.97831}, {"word": "is", "onset": 487.692, "offset": 487.894, "confidence": 0.99846}, {"word": "my", "onset": 487.932, "offset": 488.134, "confidence": 1.0}, {"word": "name.", "onset": 488.172, "offset": 488.47, "confidence": 1.0}, {"word": "I", "onset": 488.54, "offset": 488.726, "confidence": 1.0}, {"word": "do", "onset": 488.748, "offset": 488.886, "confidence": 0.99988}, {"word": "not", "onset": 488.908, "offset": 489.046, "confidence": 0.99999}, {"word": "recall", "onset": 489.068, "offset": 489.394, "confidence": 0.99967}, {"word": "that.", "onset": 489.442, "offset": 490.04, "confidence": 0.99115}, {"word": "I", "onset": 490.41, "offset": 490.726, "confidence": 1.0}, {"word": "do", "onset": 490.748, "offset": 490.934, "confidence": 0.99723}, {"word": "not", "onset": 490.972, "offset": 491.366, "confidence": 0.99945}, {"word": "recall", "onset": 491.468, "offset": 491.874, "confidence": 0.99751}, {"word": "that.", "onset": 491.922, "offset": 492.182, "confidence": 0.94534}, {"word": "Okay.", "onset": 492.236, "offset": 492.55, "confidence": 0.86}, {"word": "Mr.", "onset": 492.62, "offset": 492.902, "confidence": 0.99679}, {"word": "Ming,", "onset": 492.956, "offset": 493.598, "confidence": 0.58744}, {"word": "thank", "onset": 493.714, "offset": 493.946, "confidence": 0.999}, {"word": "you", "onset": 493.968, "offset": 494.106, "confidence": 1.0}, {"word": "for", "onset": 494.128, "offset": 494.266, "confidence": 1.0}, {"word": "coming", "onset": 494.288, "offset": 494.474, "confidence": 0.99959}, {"word": "in", "onset": 494.512, "offset": 494.666, "confidence": 1.0}, {"word": "today.", "onset": 494.688, "offset": 494.922, "confidence": 0.81}, {"word": "You", "onset": 494.976, "offset": 495.098, "confidence": 0.5}, {"word": "to", "onset": 495.104, "offset": 495.226, "confidence": 0.6}, {"word": "finish", "onset": 495.248, "offset": 495.386, "confidence": 0.99971}, {"word": "the", "onset": 495.408, "offset": 495.498, "confidence": 0.99}, {"word": "rest", "onset": 495.504, "offset": 495.626, "confidence": 0.98852}, {"word": "of", "onset": 495.648, "offset": 495.738, "confidence": 1.0}, {"word": "that", "onset": 495.744, "offset": 495.866, "confidence": 0.93347}, {"word": "danish,", "onset": 495.888, "offset": 496.534, "confidence": 0.96}, {"word": "can", "onset": 496.662, "offset": 496.906, "confidence": 0.87222}, {"word": "I", "onset": 496.928, "offset": 497.018, "confidence": 0.99}, {"word": "have", "onset": 497.024, "offset": 497.146, "confidence": 0.96372}, {"word": "that?", "onset": 497.168, "offset": 497.642, "confidence": 0.93512}, {"word": "They", "onset": 497.776, "offset": 498.074, "confidence": 0.99742}, {"word": "interrogated", "onset": 498.112, "offset": 498.742, "confidence": 0.54888}, {"word": "everybody.", "onset": 498.806, "offset": 499.322, "confidence": 0.97508}, {"word": "Had", "onset": 499.456, "offset": 499.658, "confidence": 0.63254}, {"word": "a", "onset": 499.664, "offset": 499.738, "confidence": 1.0}, {"word": "low", "onset": 499.744, "offset": 499.926, "confidence": 0.95581}, {"word": "blood", "onset": 499.968, "offset": 500.186, "confidence": 0.48635}, {"word": "sugar", "onset": 500.218, "offset": 500.602, "confidence": 0.64582}, {"word": "divert", "onset": 500.666, "offset": 501.066, "confidence": 0.44636}, {"word": "thing.", "onset": 501.098, "offset": 501.39, "confidence": 0.69999}, {"word": "It", "onset": 501.46, "offset": 501.646, "confidence": 0.97048}, {"word": "went", "onset": 501.668, "offset": 501.806, "confidence": 1.0}, {"word": "on", "onset": 501.828, "offset": 501.966, "confidence": 1.0}, {"word": "for", "onset": 501.988, "offset": 502.126, "confidence": 1.0}, {"word": "months.", "onset": 502.148, "offset": 502.382, "confidence": 0.99991}, {"word": "It", "onset": 502.436, "offset": 502.558, "confidence": 0.99976}, {"word": "was", "onset": 502.564, "offset": 502.686, "confidence": 0.9}, {"word": "a", "onset": 502.708, "offset": 502.846, "confidence": 1.0}, {"word": "total", "onset": 502.868, "offset": 503.198, "confidence": 0.99988}, {"word": "fucking", "onset": 503.284, "offset": 503.626, "confidence": 0.98927}, {"word": "harassment.", "onset": 503.658, "offset": 504.59, "confidence": 0.76616}, {"word": "Not", "onset": 506.37, "offset": 506.686, "confidence": 0.92451}, {"word": "a", "onset": 506.708, "offset": 506.846, "confidence": 1.0}, {"word": "single", "onset": 506.868, "offset": 507.294, "confidence": 0.99996}, {"word": "stratnite", "onset": 507.412, "offset": 508.202, "confidence": 0.55165}, {"word": "cracked.", "onset": 508.266, "offset": 508.762, "confidence": 0.52545}, {"word": "Gladys", "onset": 508.826, "offset": 509.258, "confidence": 0.54657}, {"word": "Carrera?", "onset": 509.274, "offset": 510.11, "confidence": 0.9758}, {"word": "Doesn't", "onset": 511.01, "offset": 511.418, "confidence": 0.99762}, {"word": "ring", "onset": 511.434, "offset": 511.578, "confidence": 0.99906}, {"word": "a", "onset": 511.594, "offset": 511.726, "confidence": 0.98}, {"word": "bell?", "onset": 511.748, "offset": 511.994, "confidence": 0.99934}, {"word": "Sorry,", "onset": 512.042, "offset": 512.494, "confidence": 0.99795}, {"word": "I", "onset": 512.612, "offset": 512.846, "confidence": 1.0}, {"word": "have", "onset": 512.868, "offset": 513.006, "confidence": 0.99887}, {"word": "no", "onset": 513.028, "offset": 513.262, "confidence": 1.0}, {"word": "recommendation", "onset": 513.316, "offset": 513.914, "confidence": 0.99537}, {"word": "of", "onset": 513.962, "offset": 514.126, "confidence": 1.0}, {"word": "that.", "onset": 514.148, "offset": 514.334, "confidence": 0.82037}, {"word": "No,", "onset": 514.372, "offset": 514.718, "confidence": 0.91}, {"word": "Jack,", "onset": 514.804, "offset": 515.47, "confidence": 0.43671}, {"word": "no", "onset": 516.07, "offset": 516.434, "confidence": 1.0}, {"word": "idea.", "onset": 516.472, "offset": 516.722, "confidence": 0.99934}, {"word": "I", "onset": 516.776, "offset": 516.898, "confidence": 1.0}, {"word": "don't", "onset": 516.904, "offset": 517.086, "confidence": 0.6681}, {"word": "recall", "onset": 517.118, "offset": 517.374, "confidence": 0.99945}, {"word": "that", "onset": 517.422, "offset": 517.586, "confidence": 0.99912}, {"word": "transaction.", "onset": 517.608, "offset": 518.046, "confidence": 0.96944}, {"word": "Do", "onset": 518.078, "offset": 518.178, "confidence": 0.56452}, {"word": "you", "onset": 518.184, "offset": 518.258, "confidence": 0.99}, {"word": "guys", "onset": 518.264, "offset": 518.386, "confidence": 0.99659}, {"word": "have", "onset": 518.408, "offset": 518.498, "confidence": 0.61398}, {"word": "any", "onset": 518.504, "offset": 518.674, "confidence": 0.88164}, {"word": "molt?", "onset": 518.712, "offset": 519.294, "confidence": 0.2918}, {"word": "Absolutely", "onset": 519.422, "offset": 520.1, "confidence": 0.9963}, {"word": "not.", "onset": 521.51, "offset": 521.97, "confidence": 0.99107}, {"word": "Francis", "onset": 522.04, "offset": 522.446, "confidence": 0.63764}, {"word": "Ortiz", "onset": 522.478, "offset": 522.926, "confidence": 0.86634}, {"word": "you", "onset": 522.958, "offset": 523.106, "confidence": 1.0}, {"word": "called", "onset": 523.128, "offset": 523.362, "confidence": 0.99907}, {"word": "so", "onset": 523.416, "offset": 523.586, "confidence": 0.9999}, {"word": "many", "onset": 523.608, "offset": 523.746, "confidence": 0.99998}, {"word": "times,", "onset": 523.768, "offset": 524.002, "confidence": 0.99915}, {"word": "I", "onset": 524.056, "offset": 524.226, "confidence": 1.0}, {"word": "just", "onset": 524.248, "offset": 524.338, "confidence": 0.99851}, {"word": "thought", "onset": 524.344, "offset": 524.466, "confidence": 0.94698}, {"word": "you", "onset": 524.488, "offset": 524.578, "confidence": 1.0}, {"word": "might", "onset": 524.584, "offset": 524.754, "confidence": 0.99785}, {"word": "remember", "onset": 524.792, "offset": 524.994, "confidence": 0.99535}, {"word": "that", "onset": 525.032, "offset": 525.282, "confidence": 0.79193}, {"word": "either.", "onset": 525.336, "offset": 525.554, "confidence": 0.51905}, {"word": "Right.", "onset": 525.592, "offset": 526.178, "confidence": 0.69}, {"word": "Would", "onset": 526.344, "offset": 526.626, "confidence": 0.98601}, {"word": "you", "onset": 526.648, "offset": 526.93, "confidence": 1.0}, {"word": "remember", "onset": 527.0, "offset": 527.33, "confidence": 0.99708}, {"word": "any", "onset": 527.4, "offset": 527.586, "confidence": 0.9944}, {"word": "of", "onset": 527.608, "offset": 527.698, "confidence": 1.0}, {"word": "that?", "onset": 527.704, "offset": 527.826, "confidence": 0.50876}, {"word": "I", "onset": 527.848, "offset": 527.938, "confidence": 0.98}, {"word": "do", "onset": 527.944, "offset": 528.018, "confidence": 0.99824}, {"word": "not", "onset": 528.024, "offset": 528.194, "confidence": 0.87563}, {"word": "recall", "onset": 528.232, "offset": 528.494, "confidence": 0.99955}, {"word": "any", "onset": 528.542, "offset": 528.706, "confidence": 0.99941}, {"word": "of", "onset": 528.728, "offset": 528.866, "confidence": 1.0}, {"word": "that.", "onset": 528.888, "offset": 529.074, "confidence": 0.95444}, {"word": "This", "onset": 529.112, "offset": 529.266, "confidence": 0.96977}, {"word": "Abdul.", "onset": 529.288, "offset": 529.902, "confidence": 0.95986}, {"word": "I", "onset": 529.966, "offset": 530.098, "confidence": 0.77}, {"word": "do", "onset": 530.104, "offset": 530.178, "confidence": 0.99046}, {"word": "not", "onset": 530.184, "offset": 530.306, "confidence": 0.97184}, {"word": "recall.", "onset": 530.328, "offset": 530.718, "confidence": 0.51147}, {"word": "No?", "onset": 530.814, "offset": 531.026, "confidence": 0.98}, {"word": "I", "onset": 531.048, "offset": 531.138, "confidence": 1.0}, {"word": "don't", "onset": 531.144, "offset": 531.326, "confidence": 0.99775}, {"word": "recall.", "onset": 531.358, "offset": 531.71, "confidence": 0.95095}, {"word": "I", "onset": 531.79, "offset": 531.986, "confidence": 0.93}, {"word": "do", "onset": 532.008, "offset": 532.098, "confidence": 0.99236}, {"word": "not.", "onset": 532.104, "offset": 532.274, "confidence": 0.74714}, {"word": "It's", "onset": 532.312, "offset": 532.526, "confidence": 0.18052}, {"word": "a", "onset": 532.558, "offset": 532.862, "confidence": 1.0}, {"word": "long", "onset": 532.936, "offset": 533.222, "confidence": 0.69573}, {"word": "phone", "onset": 533.276, "offset": 533.494, "confidence": 0.99821}, {"word": "call.", "onset": 533.532, "offset": 533.734, "confidence": 0.97301}, {"word": "Just", "onset": 533.772, "offset": 533.926, "confidence": 0.99142}, {"word": "wondering", "onset": 533.948, "offset": 534.178, "confidence": 0.94739}, {"word": "if", "onset": 534.194, "offset": 534.326, "confidence": 0.99972}, {"word": "you", "onset": 534.348, "offset": 534.486, "confidence": 1.0}, {"word": "have", "onset": 534.508, "offset": 534.646, "confidence": 0.99974}, {"word": "any", "onset": 534.668, "offset": 534.806, "confidence": 0.99998}, {"word": "memory", "onset": 534.828, "offset": 535.106, "confidence": 0.99987}, {"word": "of.", "onset": 535.138, "offset": 535.718, "confidence": 1.0}, {"word": "You", "onset": 535.884, "offset": 536.214, "confidence": 0.65}, {"word": "know,", "onset": 536.252, "offset": 536.454, "confidence": 0.97851}, {"word": "we've", "onset": 536.492, "offset": 536.706, "confidence": 0.99977}, {"word": "talked", "onset": 536.738, "offset": 536.886, "confidence": 0.99992}, {"word": "to", "onset": 536.908, "offset": 537.094, "confidence": 0.75}, {"word": "several", "onset": 537.132, "offset": 537.534, "confidence": 0.989}, {"word": "of", "onset": 537.602, "offset": 537.738, "confidence": 0.99}, {"word": "the", "onset": 537.744, "offset": 537.866, "confidence": 1.0}, {"word": "employees", "onset": 537.888, "offset": 538.198, "confidence": 0.99936}, {"word": "at", "onset": 538.214, "offset": 538.346, "confidence": 0.85}, {"word": "this", "onset": 538.368, "offset": 538.506, "confidence": 0.99667}, {"word": "firm,", "onset": 538.528, "offset": 538.726, "confidence": 0.99943}, {"word": "and", "onset": 538.758, "offset": 538.906, "confidence": 1.0}, {"word": "nobody", "onset": 538.928, "offset": 539.126, "confidence": 0.99993}, {"word": "can", "onset": 539.158, "offset": 539.306, "confidence": 0.9999}, {"word": "recall", "onset": 539.328, "offset": 539.606, "confidence": 0.99994}, {"word": "anything", "onset": 539.638, "offset": 539.882, "confidence": 0.99996}, {"word": "about", "onset": 539.936, "offset": 540.154, "confidence": 0.99991}, {"word": "the", "onset": 540.192, "offset": 540.346, "confidence": 0.99}, {"word": "Steve", "onset": 540.368, "offset": 540.566, "confidence": 0.84025}, {"word": "Madden", "onset": 540.598, "offset": 540.966, "confidence": 0.98255}, {"word": "IPO.", "onset": 540.998, "offset": 541.77, "confidence": 0.60729}, {"word": "I", "onset": 542.43, "offset": 542.698, "confidence": 1.0}, {"word": "think", "onset": 542.704, "offset": 542.826, "confidence": 1.0}, {"word": "it's", "onset": 542.848, "offset": 543.046, "confidence": 0.99771}, {"word": "odd.", "onset": 543.078, "offset": 543.77, "confidence": 0.77193}, {"word": "Do", "onset": 545.15, "offset": 545.418, "confidence": 0.90596}, {"word": "you", "onset": 545.424, "offset": 545.546, "confidence": 1.0}, {"word": "recall", "onset": 545.568, "offset": 546.326, "confidence": 0.98718}, {"word": "carnage", "onset": 546.518, "offset": 546.998, "confidence": 0.73151}, {"word": "Corporation?", "onset": 547.014, "offset": 547.77, "confidence": 0.35072}, {"word": "You", "onset": 549.55, "offset": 549.866, "confidence": 1.0}, {"word": "do", "onset": 549.888, "offset": 550.026, "confidence": 0.99773}, {"word": "recall", "onset": 550.048, "offset": 550.246, "confidence": 0.99911}, {"word": "it?", "onset": 550.278, "offset": 550.474, "confidence": 0.88714}, {"word": "No,", "onset": 550.512, "offset": 550.666, "confidence": 0.67}, {"word": "I", "onset": 550.688, "offset": 550.778, "confidence": 1.0}, {"word": "don't", "onset": 550.784, "offset": 550.906, "confidence": 0.99861}, {"word": "recall", "onset": 550.928, "offset": 551.174, "confidence": 0.99913}, {"word": "that", "onset": 551.222, "offset": 551.386, "confidence": 0.98968}, {"word": "at", "onset": 551.408, "offset": 551.546, "confidence": 1.0}, {"word": "all.", "onset": 551.568, "offset": 552.14, "confidence": 1.0}, {"word": "Excuse", "onset": 552.59, "offset": 553.126, "confidence": 0.99064}, {"word": "me,", "onset": 553.158, "offset": 553.402, "confidence": 1.0}, {"word": "I", "onset": 553.456, "offset": 553.626, "confidence": 0.66}, {"word": "have", "onset": 553.648, "offset": 553.786, "confidence": 0.65135}, {"word": "to", "onset": 553.808, "offset": 553.946, "confidence": 1.0}, {"word": "ask,", "onset": 553.968, "offset": 554.346, "confidence": 0.99896}, {"word": "is", "onset": 554.448, "offset": 554.618, "confidence": 0.9999}, {"word": "that", "onset": 554.624, "offset": 554.746, "confidence": 0.93626}, {"word": "your", "onset": 554.768, "offset": 554.906, "confidence": 1.0}, {"word": "real", "onset": 554.928, "offset": 555.114, "confidence": 1.0}, {"word": "hair?", "onset": 555.152, "offset": 555.878, "confidence": 0.99954}, {"word": "Are", "onset": 556.054, "offset": 556.298, "confidence": 0.9996}, {"word": "you", "onset": 556.304, "offset": 556.39, "confidence": 0.99}, {"word": "going", "onset": 556.4, "offset": 556.478, "confidence": 0.99022}, {"word": "to", "onset": 556.484, "offset": 556.558, "confidence": 1.0}, {"word": "say", "onset": 556.564, "offset": 556.686, "confidence": 0.99639}, {"word": "anything", "onset": 556.708, "offset": 556.942, "confidence": 0.9996}, {"word": "about", "onset": 556.996, "offset": 557.166, "confidence": 0.99999}, {"word": "that?", "onset": 557.188, "offset": 557.76, "confidence": 0.99994}, {"word": "Are", "onset": 558.13, "offset": 558.446, "confidence": 0.99133}, {"word": "you", "onset": 558.468, "offset": 558.558, "confidence": 1.0}, {"word": "going", "onset": 558.564, "offset": 558.638, "confidence": 0.98484}, {"word": "to", "onset": 558.644, "offset": 558.814, "confidence": 1.0}, {"word": "comment", "onset": 558.852, "offset": 559.146, "confidence": 0.99953}, {"word": "on", "onset": 559.178, "offset": 559.278, "confidence": 1.0}, {"word": "my", "onset": 559.284, "offset": 559.358, "confidence": 1.0}, {"word": "hair?", "onset": 559.364, "offset": 559.546, "confidence": 0.99994}, {"word": "Is", "onset": 559.578, "offset": 559.726, "confidence": 0.99603}, {"word": "that", "onset": 559.748, "offset": 559.838, "confidence": 0.99844}, {"word": "how", "onset": 559.844, "offset": 559.966, "confidence": 0.9993}, {"word": "we're", "onset": 559.988, "offset": 560.138, "confidence": 0.99986}, {"word": "doing?", "onset": 560.154, "offset": 560.334, "confidence": 0.99952}, {"word": "Is", "onset": 560.372, "offset": 560.478, "confidence": 0.63626}, {"word": "this", "onset": 560.484, "offset": 560.654, "confidence": 0.96472}, {"word": "personal", "onset": 560.692, "offset": 560.894, "confidence": 0.99994}, {"word": "questions?", "onset": 560.932, "offset": 561.182, "confidence": 0.98163}, {"word": "I", "onset": 561.236, "offset": 561.358, "confidence": 0.96}, {"word": "thought", "onset": 561.364, "offset": 561.534, "confidence": 0.92683}, {"word": "wondering", "onset": 561.572, "offset": 561.818, "confidence": 0.99806}, {"word": "why", "onset": 561.834, "offset": 561.966, "confidence": 0.99999}, {"word": "you", "onset": 561.988, "offset": 562.078, "confidence": 1.0}, {"word": "would", "onset": 562.084, "offset": 562.206, "confidence": 0.99936}, {"word": "wear", "onset": 562.228, "offset": 562.426, "confidence": 0.99968}, {"word": "something", "onset": 562.458, "offset": 562.654, "confidence": 0.99999}, {"word": "like", "onset": 562.692, "offset": 562.846, "confidence": 0.99999}, {"word": "that.", "onset": 562.868, "offset": 563.44, "confidence": 0.99292}, {"word": "Yes.", "onset": 568.69, "offset": 569.45, "confidence": 0.94}, {"word": "I", "onset": 569.62, "offset": 569.858, "confidence": 1.0}, {"word": "have", "onset": 569.864, "offset": 569.938, "confidence": 0.99957}, {"word": "a", "onset": 569.944, "offset": 570.018, "confidence": 1.0}, {"word": "rare", "onset": 570.024, "offset": 570.286, "confidence": 0.67876}, {"word": "condition", "onset": 570.318, "offset": 570.654, "confidence": 0.9465}, {"word": "which", "onset": 570.702, "offset": 570.914, "confidence": 0.99878}, {"word": "requires", "onset": 570.952, "offset": 571.326, "confidence": 0.99974}, {"word": "me", "onset": 571.358, "offset": 571.506, "confidence": 1.0}, {"word": "to", "onset": 571.528, "offset": 571.618, "confidence": 1.0}, {"word": "drink", "onset": 571.624, "offset": 571.854, "confidence": 0.9612}, {"word": "one", "onset": 571.902, "offset": 572.018, "confidence": 1.0}, {"word": "of", "onset": 572.024, "offset": 572.098, "confidence": 1.0}, {"word": "those", "onset": 572.104, "offset": 572.226, "confidence": 0.99994}, {"word": "every", "onset": 572.248, "offset": 572.434, "confidence": 0.99927}, {"word": "15", "onset": 572.472, "offset": 572.77, "confidence": 1.0}, {"word": "minutes.", "onset": 572.84, "offset": 573.17, "confidence": 0.99984}, {"word": "Please.", "onset": 573.24, "offset": 573.86, "confidence": 0.99901}, {"word": "We", "onset": 574.55, "offset": 574.866, "confidence": 0.99996}, {"word": "were", "onset": 574.888, "offset": 575.122, "confidence": 0.7718}, {"word": "specifically", "onset": 575.176, "offset": 575.822, "confidence": 0.99962}, {"word": "advised", "onset": 575.886, "offset": 576.398, "confidence": 0.71811}, {"word": "not", "onset": 576.494, "offset": 576.754, "confidence": 0.99998}, {"word": "to", "onset": 576.792, "offset": 576.946, "confidence": 1.0}, {"word": "leave", "onset": 576.968, "offset": 577.154, "confidence": 0.99998}, {"word": "the", "onset": 577.192, "offset": 577.346, "confidence": 1.0}, {"word": "country.", "onset": 577.368, "offset": 577.794, "confidence": 0.9993}, {"word": "So", "onset": 577.912, "offset": 578.446, "confidence": 0.5311}, {"word": "we", "onset": 578.568, "offset": 578.854, "confidence": 0.99718}, {"word": "took", "onset": 578.892, "offset": 579.046, "confidence": 0.99997}, {"word": "our", "onset": 579.068, "offset": 579.206, "confidence": 1.0}, {"word": "wives", "onset": 579.228, "offset": 579.474, "confidence": 0.99942}, {"word": "to", "onset": 579.522, "offset": 579.638, "confidence": 1.0}, {"word": "Italy.", "onset": 579.644, "offset": 580.274, "confidence": 0.99973}, {"word": "We", "onset": 580.402, "offset": 580.646, "confidence": 0.99915}, {"word": "figured", "onset": 580.668, "offset": 580.946, "confidence": 0.99989}, {"word": "we", "onset": 580.978, "offset": 581.078, "confidence": 0.9938}, {"word": "were", "onset": 581.084, "offset": 581.254, "confidence": 0.97166}, {"word": "safer", "onset": 581.292, "offset": 581.602, "confidence": 0.99777}, {"word": "working", "onset": 581.666, "offset": 581.894, "confidence": 0.99978}, {"word": "from", "onset": 581.932, "offset": 582.134, "confidence": 0.99976}, {"word": "overseas,", "onset": 582.172, "offset": 582.802, "confidence": 0.99985}, {"word": "giving", "onset": 582.866, "offset": 583.094, "confidence": 0.99986}, {"word": "orders", "onset": 583.132, "offset": 583.458, "confidence": 0.96}, {"word": "to", "onset": 583.474, "offset": 583.606, "confidence": 1.0}, {"word": "Rugrat.", "onset": 583.628, "offset": 584.29, "confidence": 0.95541}, {"word": "Nobody", "onset": 584.37, "offset": 584.674, "confidence": 0.99976}, {"word": "could", "onset": 584.722, "offset": 584.886, "confidence": 0.99981}, {"word": "arrest", "onset": 584.908, "offset": 585.266, "confidence": 0.9993}, {"word": "us.", "onset": 585.298, "offset": 585.542, "confidence": 1.0}, {"word": "And", "onset": 585.596, "offset": 585.814, "confidence": 0.87}, {"word": "nobody", "onset": 585.852, "offset": 586.114, "confidence": 0.99986}, {"word": "could", "onset": 586.162, "offset": 586.326, "confidence": 0.99979}, {"word": "prove", "onset": 586.348, "offset": 586.546, "confidence": 0.99985}, {"word": "I", "onset": 586.578, "offset": 586.678, "confidence": 1.0}, {"word": "was", "onset": 586.684, "offset": 586.854, "confidence": 0.96}, {"word": "still", "onset": 586.892, "offset": 587.046, "confidence": 0.99976}, {"word": "running", "onset": 587.068, "offset": 587.302, "confidence": 0.9999}, {"word": "Stratton", "onset": 587.356, "offset": 587.826, "confidence": 0.97448}, {"word": "from", "onset": 587.858, "offset": 588.006, "confidence": 0.99933}, {"word": "a", "onset": 588.028, "offset": 588.118, "confidence": 0.99}, {"word": "yacht.", "onset": 588.124, "offset": 588.626, "confidence": 0.4615}, {"word": "Hey,", "onset": 588.738, "offset": 589.062, "confidence": 0.95264}, {"word": "Rugrat.", "onset": 589.116, "offset": 590.178, "confidence": 0.94358}, {"word": "Bonjour.", "onset": 590.354, "offset": 591.218, "confidence": 0.7554}, {"word": "You", "onset": 591.314, "offset": 591.622, "confidence": 1.0}, {"word": "bob", "onset": 591.676, "offset": 591.986, "confidence": 0.55094}, {"word": "headed", "onset": 592.018, "offset": 592.306, "confidence": 0.89994}, {"word": "Eagle,", "onset": 592.338, "offset": 592.706, "confidence": 0.73558}, {"word": "how", "onset": 592.738, "offset": 592.886, "confidence": 0.99859}, {"word": "you", "onset": 592.908, "offset": 592.998, "confidence": 0.96}, {"word": "doing?", "onset": 593.004, "offset": 593.27, "confidence": 0.98471}, {"word": "Donnie,", "onset": 593.34, "offset": 593.666, "confidence": 0.51469}, {"word": "Donnie,", "onset": 593.698, "offset": 593.986, "confidence": 0.88888}, {"word": "listen,", "onset": 594.018, "offset": 594.454, "confidence": 0.99693}, {"word": "we", "onset": 594.572, "offset": 594.806, "confidence": 0.99898}, {"word": "have", "onset": 594.828, "offset": 594.966, "confidence": 0.99986}, {"word": "a", "onset": 594.988, "offset": 595.078, "confidence": 1.0}, {"word": "problem,", "onset": 595.084, "offset": 595.35, "confidence": 0.99875}, {"word": "okay?", "onset": 595.42, "offset": 595.702, "confidence": 0.87}, {"word": "Your", "onset": 595.756, "offset": 596.022, "confidence": 1.0}, {"word": "friend", "onset": 596.076, "offset": 596.534, "confidence": 0.9997}, {"word": "Steve", "onset": 596.652, "offset": 597.026, "confidence": 0.99953}, {"word": "Madden", "onset": 597.058, "offset": 597.474, "confidence": 0.99398}, {"word": "is", "onset": 597.522, "offset": 597.686, "confidence": 0.99989}, {"word": "unloading", "onset": 597.708, "offset": 598.45, "confidence": 0.99146}, {"word": "shares.", "onset": 598.53, "offset": 599.362, "confidence": 0.39451}, {"word": "What", "onset": 599.506, "offset": 599.766, "confidence": 0.92694}, {"word": "do", "onset": 599.788, "offset": 599.878, "confidence": 0.52722}, {"word": "you", "onset": 599.884, "offset": 600.03, "confidence": 0.89}, {"word": "shade?", "onset": 600.06, "offset": 600.346, "confidence": 0.22922}, {"word": "Who", "onset": 600.378, "offset": 600.526, "confidence": 0.99969}, {"word": "told", "onset": 600.548, "offset": 600.686, "confidence": 0.99993}, {"word": "you", "onset": 600.708, "offset": 600.846, "confidence": 1.0}, {"word": "that?", "onset": 600.868, "offset": 601.102, "confidence": 0.99491}, {"word": "What's", "onset": 601.156, "offset": 601.466, "confidence": 0.95893}, {"word": "going", "onset": 601.498, "offset": 601.646, "confidence": 0.9931}, {"word": "on?", "onset": 601.668, "offset": 601.74, "confidence": 0.66}]}]}]}}